{"is_source_file": false, "format": "", "description": "", "external_files": [], "external_methods": [], "published": [], "classes": [], "methods": [], "calls": [], "search-terms": [], "state": 2, "file_id": 6, "knowledge_revision": 16, "git_revision": "62be0be61f15b16285e9bceab54adb3918f52cb2", "hash": "415959b995a10be89a1fb2a1cfc25146", "format-version": 4, "code-base-name": "expense_tracker_database", "filename": "expense_tracker_database/startup.sh", "revision_history": [{"16": "62be0be61f15b16285e9bceab54adb3918f52cb2"}]}